activeledgersdk/__about__.py
activeledgersdk/__init__.py
activeledgersdk/classes/__init__.py
activeledgersdk/classes/key.py
activeledgersdk/classes/transaction.py
activeledgersdk/classes/user.py
activeledgersdk/primitives/__init__.py
activeledgersdk/primitives/keypairs.py
activeledgersdk-1.0.dev1.dist-info/METADATA
activeledgersdk-1.0.dev1.dist-info/RECORD
activeledgersdk-1.0.dev1.dist-info/WHEEL
activeledgersdk-1.0.dev1.dist-info/top_level.txt
