Metadata-Version: 2.1
Name: activeledgersdk
Version: 1.0.dev1
Summary: activeledgersdk is a package to use full functions of activeledger for Python developers
Home-page: https://github.com/jialin-yu/activeLedgerSDK
Author: activeledger
Author-email: infor@activeledger.io
License: BSD or Apache License, Version 2.0
Platform: UNKNOWN
